ctodd_python_lib_datetime-1.0.0.dist-info/LICENSE.txt
ctodd_python_lib_datetime-1.0.0.dist-info/METADATA
ctodd_python_lib_datetime-1.0.0.dist-info/RECORD
ctodd_python_lib_datetime-1.0.0.dist-info/WHEEL
ctodd_python_lib_datetime-1.0.0.dist-info/top_level.txt
datetime_helpers/__init__.py
datetime_helpers/date_manipulation_helpers.py
datetime_helpers/tests/__init__.py
datetime_helpers/tests/test_date_manipulation_helpers.py
